[{"id":"I01270","brand":"優生","category":"母嬰用品","sku":"I01270","barcode":"4710091188728","name":"409*優生NEO姆指型安撫奶嘴S*12個","spec":"個","unit":"個","taxPrice":65,"suggestedPrice":79,"casePack":12,"image":"","active":true},{"id":"I01280","brand":"優生","category":"母嬰用品","sku":"I01280","barcode":"4710091188742","name":"409*優生NEO姆指型安撫奶嘴L*12個","spec":"個","unit":"個","taxPrice":65,"suggestedPrice":79,"casePack":12,"image":"","active":true},{"id":"I01300","brand":"優生","category":"母嬰用品","sku":"I01300","barcode":"4710091171737","name":"410*優生真母感奶瓶奶嘴一般S(2+1)*12組","spec":"組","unit":"組","taxPrice":83,"suggestedPrice":99,"casePack":12,"image":"","active":true},{"id":"I01301","brand":"優生","category":"母嬰用品","sku":"I01301","barcode":"4710091171744","name":"410*優生真母感奶瓶奶嘴一般M(2+1)*12組","spec":"組","unit":"組","taxPrice":83,"suggestedPrice":99,"casePack":12,"image":"","active":true},{"id":"I01302","brand":"優生","category":"母嬰用品","sku":"I01302","barcode":"4710091171751","name":"410*優生真母感奶瓶奶嘴一般L(2+1)*12組","spec":"組","unit":"組","taxPrice":83,"suggestedPrice":99,"casePack":12,"image":"","active":true},{"id":"I01305","brand":"優生","category":"母嬰用品","sku":"I01305","barcode":"4710091171775","name":"413*優生真母感奶瓶奶嘴寬口S(2+1)*12組","spec":"組","unit":"組","taxPrice":104,"suggestedPrice":129,"casePack":12,"image":"","active":true},{"id":"I01306","brand":"優生","category":"母嬰用品","sku":"I01306","barcode":"4710091171782","name":"413*優生真母感奶瓶奶嘴寬口M(2+1)*12組","spec":"組","unit":"組","taxPrice":104,"suggestedPrice":129,"casePack":12,"image":"","active":true},{"id":"I01307","brand":"優生","category":"母嬰用品","sku":"I01307","barcode":"4710091171799","name":"413*優生真母感奶瓶奶嘴寬口L(2+1)*12組","spec":"組","unit":"組","taxPrice":104,"suggestedPrice":129,"casePack":12,"image":"","active":true},{"id":"I01310","brand":"優生","category":"母嬰用品","sku":"I01310","barcode":"4710091178644","name":"411*優生矽晶安撫奶嘴標準型S*12個","spec":"個","unit":"個","taxPrice":122,"suggestedPrice":149,"casePack":12,"image":"","active":true},{"id":"I01320","brand":"優生","category":"母嬰用品","sku":"I01320","barcode":"4710091178651","name":"411*優生矽晶安撫奶嘴標準型L*12個","spec":"個","unit":"個","taxPrice":122,"suggestedPrice":149,"casePack":12,"image":"","active":true},{"id":"I01330","brand":"優生","category":"母嬰用品","sku":"I01330","barcode":"4710091178668","name":"412*優生矽晶安撫奶嘴雙扁型S*12個","spec":"個","unit":"個","taxPrice":130,"suggestedPrice":159,"casePack":12,"image":"","active":true},{"id":"I01340","brand":"優生","category":"母嬰用品","sku":"I01340","barcode":"4710091178675","name":"412*優生矽晶安撫奶嘴雙扁型L*12個","spec":"個","unit":"個","taxPrice":130,"suggestedPrice":159,"casePack":12,"image":"","active":true},{"id":"I01350","brand":"優生","category":"母嬰用品","sku":"I01350","barcode":"4710091178682","name":"412*優生矽晶安撫奶嘴拇指型S*12個","spec":"個","unit":"個","taxPrice":130,"suggestedPrice":159,"casePack":12,"image":"","active":true},{"id":"I01360","brand":"優生","category":"母嬰用品","sku":"I01360","barcode":"4710091178699","name":"412*優生矽晶安撫奶嘴拇指型L*12個","spec":"個","unit":"個","taxPrice":130,"suggestedPrice":159,"casePack":12,"image":"","active":true},{"id":"I02110","brand":"優生","category":"母嬰用品","sku":"I02110","barcode":"4710091110682","name":"430*優生大容量奶粉盒*12個","spec":"個","unit":"個","taxPrice":58,"suggestedPrice":75,"casePack":12,"image":"","active":true},{"id":"I02130","brand":"優生","category":"母嬰用品","sku":"I02130","barcode":"4710091186021","name":"431*優生輕鬆扣奶嘴鏈*24個","spec":"個","unit":"個","taxPrice":56,"suggestedPrice":69,"casePack":24,"image":"","active":true},{"id":"I03030","brand":"優生","category":"母嬰用品","sku":"I03030","barcode":"4710091111023","name":"434*優生乳牙刷*12個","spec":"個","unit":"個","taxPrice":42,"suggestedPrice":55,"casePack":12,"image":"","active":true},{"id":"I03040","brand":"優生","category":"母嬰用品","sku":"I03040","barcode":"4710091115106","name":"436*優生咬牙固齒器(熊造型)*12個","spec":"個","unit":"個","taxPrice":55,"suggestedPrice":69,"casePack":12,"image":"","active":true},{"id":"I03050","brand":"優生","category":"母嬰用品","sku":"I03050","barcode":"4710091112808","name":"437*優生防逆流吸鼻器*12個","spec":"個","unit":"個","taxPrice":78,"suggestedPrice":99,"casePack":12,"image":"","active":true},{"id":"I03062","brand":"優生","category":"母嬰用品","sku":"I03062","barcode":"4710091188445","name":"438*優生奶嘴式餵藥器*12個","spec":"個","unit":"個","taxPrice":80,"suggestedPrice":99,"casePack":12,"image":"","active":true},{"id":"I03095","brand":"優生","category":"母嬰用品","sku":"I03095","barcode":"4710091123446","name":"444*優生抗菌旋轉奶瓶刷(附奶嘴刷)*12支","spec":"支","unit":"支","taxPrice":75,"suggestedPrice":99,"casePack":12,"image":"","active":true},{"id":"I03210","brand":"優生","category":"母嬰用品","sku":"I03210","barcode":"4710091110248","name":"447*優生嬰兒爽身粉300g*12罐","spec":"罐","unit":"罐","taxPrice":88,"suggestedPrice":109,"casePack":12,"image":"","active":true},{"id":"I03220","brand":"優生","category":"母嬰用品","sku":"I03220","barcode":"4710091110255","name":"447*優生涼性爽身粉300g*12罐","spec":"罐","unit":"罐","taxPrice":88,"suggestedPrice":109,"casePack":12,"image":"","active":true},{"id":"I03230","brand":"優生","category":"母嬰用品","sku":"I03230","barcode":"4710091165231","name":"447*優生涼性爽身粉-綠茶300g*12罐","spec":"罐","unit":"罐","taxPrice":70,"suggestedPrice":89,"casePack":12,"image":"","active":true},{"id":"I03250","brand":"優生","category":"母嬰用品","sku":"I03250","barcode":"4710091162278","name":"448*優生柔濕巾清爽型80抽*24包","spec":"包","unit":"包","taxPrice":36,"suggestedPrice":45,"casePack":24,"image":"images/wet-wipes/I03250.webp","active":true},{"id":"I03310","brand":"優生","category":"母嬰用品","sku":"I03310","barcode":"4710091220213","name":"449*嬌娃嬰兒爽身粉300g*12罐","spec":"罐","unit":"罐","taxPrice":78,"suggestedPrice":99,"casePack":12,"image":"","active":true},{"id":"I03320","brand":"優生","category":"母嬰用品","sku":"I03320","barcode":"4710091220220","name":"449*嬌娃涼性爽身粉300g*12罐","spec":"罐","unit":"罐","taxPrice":78,"suggestedPrice":99,"casePack":12,"image":"","active":true},{"id":"I03330","brand":"優生","category":"母嬰用品","sku":"I03330","barcode":"4710091220152","name":"450*嬌娃粉撲*12個","spec":"個","unit":"個","taxPrice":40,"suggestedPrice":49,"casePack":12,"image":"","active":true},{"id":"I03410","brand":"優生","category":"家用紙","sku":"I03410","barcode":"4710091125037","name":"452*潔P濕式衛生紙40抽*24包","spec":"包","unit":"包","taxPrice":39,"suggestedPrice":49,"casePack":24,"image":"","active":true},{"id":"I03420","brand":"優生","category":"家用紙","sku":"I03420","barcode":"4710091125389","name":"452*潔P濕式衛生紙40抽3入*8袋","spec":"袋","unit":"袋","taxPrice":108,"suggestedPrice":129,"casePack":8,"image":"","active":true},{"id":"I03430","brand":"優生","category":"家用紙","sku":"I03430","barcode":"4710091125051","name":"452*潔P濕式衛生紙迷你包8抽3入*48袋","spec":"袋","unit":"袋","taxPrice":32,"suggestedPrice":39,"casePack":48,"image":"","active":true},{"id":"I03440","brand":"優生","category":"家用紙","sku":"I03440","barcode":"4710091125150","name":"452*潔P濕式衛生紙2片10入*48袋","spec":"袋","unit":"袋","taxPrice":28,"suggestedPrice":35,"casePack":48,"image":"","active":true},{"id":"I04010","brand":"優生","category":"母嬰用品","sku":"I04010","barcode":"4710091661474","name":"456*史奴比旋轉奶瓶刷(附奶嘴刷)*12支","spec":"支","unit":"支","taxPrice":58,"suggestedPrice":75,"casePack":12,"image":"","active":true},{"id":"I04020","brand":"優生","category":"母嬰用品","sku":"I04020","barcode":"4710091661481","name":"457*史奴比直立奶瓶刷(附奶嘴刷)*12支","spec":"支","unit":"支","taxPrice":52,"suggestedPrice":65,"casePack":12,"image":"","active":true},{"id":"I04120","brand":"優生","category":"母嬰用品","sku":"I04120","barcode":"4714221090530","name":"464*史奴比PP軸棉棒100支6入*12袋","spec":"袋","unit":"袋","taxPrice":68,"suggestedPrice":85,"casePack":12,"image":"","active":true},{"id":"I04160","brand":"優生","category":"母嬰用品","sku":"I04160","barcode":"4710091330394","name":"471*史奴比牙線棒50支2+1盒*12組","spec":"組","unit":"組","taxPrice":52,"suggestedPrice":65,"casePack":12,"image":"","active":true},{"id":"I04170","brand":"優生","category":"母嬰用品","sku":"I04170","barcode":"4714221090554","name":"472*史奴比細塑軸棉棒圓罐200支*24罐","spec":"罐","unit":"罐","taxPrice":35,"suggestedPrice":45,"casePack":24,"image":"","active":true},{"id":"I04180","brand":"優生","category":"母嬰用品","sku":"I04180","barcode":"4714221090547","name":"473*史奴比細紙軸螺璇棉棒200支*24罐","spec":"罐","unit":"罐","taxPrice":52,"suggestedPrice":65,"casePack":24,"image":"","active":true},{"id":"I30210","brand":"優生","category":"母嬰用品","sku":"I30210","barcode":"4711542220721","name":"485*喜多PP奶瓶一般S120g2入*6組","spec":"組","unit":"組","taxPrice":90,"suggestedPrice":110,"casePack":6,"image":"","active":true},{"id":"I30220","brand":"優生","category":"母嬰用品","sku":"I30220","barcode":"4711542220738","name":"486*喜多PP奶瓶一般L240g2入*6組","spec":"組","unit":"組","taxPrice":95,"suggestedPrice":120,"casePack":6,"image":"","active":true},{"id":"I30230","brand":"優生","category":"母嬰用品","sku":"I30230","barcode":"4711542220745","name":"487*喜多PP奶瓶寬口S140g2入*6組","spec":"組","unit":"組","taxPrice":105,"suggestedPrice":130,"casePack":6,"image":"","active":true},{"id":"I30240","brand":"優生","category":"母嬰用品","sku":"I30240","barcode":"4711542220752","name":"488*喜多PP奶瓶寬口L270g2入*6組","spec":"組","unit":"組","taxPrice":110,"suggestedPrice":140,"casePack":6,"image":"","active":true},{"id":"I30310","brand":"優生","category":"母嬰用品","sku":"I30310","barcode":"4711542220349","name":"476*喜多免洗褲(男用)M*72包","spec":"包","unit":"包","taxPrice":90,"suggestedPrice":0,"casePack":72,"image":"","active":true},{"id":"I30320","brand":"優生","category":"母嬰用品","sku":"I30320","barcode":"4711542220356","name":"476*喜多免洗褲(男用)L*72包","spec":"包","unit":"包","taxPrice":90,"suggestedPrice":0,"casePack":72,"image":"","active":true},{"id":"I30330","brand":"優生","category":"母嬰用品","sku":"I30330","barcode":"4711542220363","name":"476*喜多免洗褲(男用)XL*72包","spec":"包","unit":"包","taxPrice":90,"suggestedPrice":0,"casePack":72,"image":"","active":true},{"id":"I30340","brand":"優生","category":"母嬰用品","sku":"I30340","barcode":"4711542220370","name":"476*喜多免洗褲(女用)M*72包","spec":"包","unit":"包","taxPrice":90,"suggestedPrice":0,"casePack":72,"image":"","active":true},{"id":"I30350","brand":"優生","category":"母嬰用品","sku":"I30350","barcode":"4711542220387","name":"476*喜多免洗褲(女用)L*72包","spec":"包","unit":"包","taxPrice":90,"suggestedPrice":0,"casePack":72,"image":"","active":true},{"id":"I30360","brand":"優生","category":"母嬰用品","sku":"I30360","barcode":"4711542220394","name":"476*喜多免洗褲(女用)XL*72包","spec":"包","unit":"包","taxPrice":90,"suggestedPrice":0,"casePack":72,"image":"","active":true},{"id":"I30380","brand":"優生","category":"母嬰用品","sku":"I30380","barcode":"4711542220486","name":"478*喜多免洗褲(孕婦)L*72包","spec":"包","unit":"包","taxPrice":112,"suggestedPrice":0,"casePack":72,"image":"","active":true},{"id":"I30390","brand":"優生","category":"母嬰用品","sku":"I30390","barcode":"4711542220493","name":"478*喜多免洗褲(孕婦)XL*72包","spec":"包","unit":"包","taxPrice":112,"suggestedPrice":0,"casePack":72,"image":"","active":true},{"id":"I30395","brand":"優生","category":"母嬰用品","sku":"I30395","barcode":"4711542220509","name":"478*喜多免洗褲(孕婦)XXL*72包","spec":"包","unit":"包","taxPrice":112,"suggestedPrice":0,"casePack":72,"image":"","active":true},{"id":"I33540","brand":"優生","category":"母嬰用品","sku":"I33540","barcode":"4711542226006","name":"590*喜多PP軸棉棒200支方盒*24盒","spec":"盒","unit":"盒","taxPrice":39,"suggestedPrice":49,"casePack":24,"image":"","active":true},{"id":"I33550","brand":"優生","category":"母嬰用品","sku":"I33550","barcode":"4711542226013","name":"592*喜多細紙軸棉棒200支圓罐*24罐","spec":"罐","unit":"罐","taxPrice":68,"suggestedPrice":85,"casePack":24,"image":"","active":true},{"id":"I40010","brand":"優生","category":"母嬰用品","sku":"I40010","barcode":"4582420010518","name":"595*小本熊暖暖包10片*24袋","spec":"袋","unit":"袋","taxPrice":55,"suggestedPrice":69,"casePack":24,"image":"","active":true},{"id":"I40020","brand":"優生","category":"母嬰用品","sku":"I40020","barcode":"4582420010617","name":"596*小本熊暖暖貼10片*24袋","spec":"袋","unit":"袋","taxPrice":110,"suggestedPrice":139,"casePack":24,"image":"","active":true},{"id":"I99000","brand":"優生","category":"不分類","sku":"I99000","barcode":"I99000","name":"潔P濕式衛生紙紙架*1","spec":"座","unit":"座","taxPrice":0,"suggestedPrice":0,"casePack":1,"image":"","active":true}]